chineseEasyWordcloud/__init__.py
chineseEasyWordcloud/cut.py
chineseEasyWordcloud/easyWordcloud.py
chineseEasyWordcloud/stopwords.py
chineseEasyWordcloud/terminal.py
chineseEasyWordcloud/data/__init__.py
chineseEasyWordcloud/data/stopwords.py
doFolder/__init__.py
doFolder/compare.py
doFolder/main.py
doFolder/terminal.py
chineseEasyWordcloud-0.0.1.dist-info/METADATA
chineseEasyWordcloud-0.0.1.dist-info/WHEEL
chineseEasyWordcloud-0.0.1.dist-info/entry_points.txt
chineseEasyWordcloud-0.0.1.dist-info/top_level.txt
chineseEasyWordcloud-0.0.1.dist-info/RECORD
