Metadata-Version: 2.1
Name: chineseEasyWordcloud
Version: 0.0.1
Summary: 帮助初学者更轻松地制作中文词云。
Home-page: https://kuankuan2007.gitee.io/docs/docsPage/?name=chinese-easy-wordcloud
Author: kuankuan
Author-email: 2163826131@qq.com
License: Mulan PSL v2
Keywords: wordcloud,jieba,词云,中文,Chinese
Platform: windows
Platform: linux
Platform: macos
Classifier: Natural Language :: Chinese (Simplified)
Classifier: Development Status :: 3 - Alpha
Classifier: Intended Audience :: Information Technology
Classifier: Programming Language :: Python :: 3
Classifier: Operating System :: MacOS
Classifier: Operating System :: POSIX :: Linux
Classifier: Operating System :: Microsoft :: Windows
Classifier: License :: OSI Approved :: Mulan Permissive Software License v2 (MulanPSL-2.0)
Requires-Dist: wordcloud
Requires-Dist: jieba
Requires-Dist: doFolder
